conrich-0.7.9.data/purelib/conrich/__init__.py
conrich-0.7.9.data/purelib/conrich/Futures/Clog4net.config
conrich-0.7.9.data/purelib/conrich/Futures/Concord.API.Future.Client.dll
conrich-0.7.9.data/purelib/conrich/Futures/Concord.SDK.Logging.dll
conrich-0.7.9.data/purelib/conrich/Futures/Concord.SDK.Utility.dll
conrich-0.7.9.data/purelib/conrich/Futures/ConcordsCAPIATL.dll
conrich-0.7.9.data/purelib/conrich/Futures/ConcordsCAPIATLx64.dll
conrich-0.7.9.data/purelib/conrich/Futures/Futures_README.md
conrich-0.7.9.data/purelib/conrich/Futures/Interop.ConcordsCAPIATLLib.dll
conrich-0.7.9.data/purelib/conrich/Futures/__init__.py
conrich-0.7.9.data/purelib/conrich/Futures/constant.py
conrich-0.7.9.data/purelib/conrich/Futures/foreign_futures.py
conrich-0.7.9.data/purelib/conrich/Futures/futures.py
conrich-0.7.9.data/purelib/conrich/Futures/header.json
conrich-0.7.9.data/purelib/conrich/Futures/log4net.dll
conrich-0.7.9.data/purelib/conrich/Futures/return_code.json
conrich-0.7.9.data/purelib/conrich/Futures/tag.json
conrich-0.7.9.data/purelib/conrich/Futures/winmm.dll
conrich-0.7.9.data/purelib/conrich/Futures/foreign/Clog4net.config
conrich-0.7.9.data/purelib/conrich/Quote/__init__.py
conrich-0.7.9.data/purelib/conrich/Quote/event.py
conrich-0.7.9.data/purelib/conrich/Quote/server.py
conrich-0.7.9.data/purelib/conrich/Stock/APILibrary.dll
conrich-0.7.9.data/purelib/conrich/Stock/Clog4net.config
conrich-0.7.9.data/purelib/conrich/Stock/Concord.SDK.IOCPHelper.dll
conrich-0.7.9.data/purelib/conrich/Stock/Concord.SDK.Logging.dll
conrich-0.7.9.data/purelib/conrich/Stock/Concord.SDK.Utility.dll
conrich-0.7.9.data/purelib/conrich/Stock/ConcordSTradeAPI.dll
conrich-0.7.9.data/purelib/conrich/Stock/ConcordsCAPIATL.dll
conrich-0.7.9.data/purelib/conrich/Stock/ConcordsCAPIATLx64.dll
conrich-0.7.9.data/purelib/conrich/Stock/__init__.py
conrich-0.7.9.data/purelib/conrich/Stock/constant.py
conrich-0.7.9.data/purelib/conrich/Stock/header.json
conrich-0.7.9.dist-info/LICENSE
conrich-0.7.9.dist-info/METADATA
conrich-0.7.9.dist-info/WHEEL
conrich-0.7.9.dist-info/top_level.txt
conrich-0.7.9.dist-info/RECORD
