Metadata-Version: 2.1
Name: conrich
Version: 0.7.9
Summary: Python client for send order to Concords Securities.
Home-page: https://concords6016.github.io/conrich_docs/
Author: Leo Wu
Author-email: leo.wu@concords.com.tw
License: MIT
Keywords: stock,futures,option,TWSE,TPEX,TAIFEX
Platform: Windows
Classifier: Development Status :: 4 - Beta
Classifier: License :: OSI Approved :: MIT License
Classifier: Intended Audience :: Developers
Classifier: Programming Language :: Python :: 3
Classifier: Programming Language :: Python :: 3.6
Classifier: Programming Language :: Python :: 3.7
Classifier: Programming Language :: Python :: 3.8
Classifier: Operating System :: Microsoft :: Windows
Classifier: Topic :: Office/Business :: Financial
Classifier: Topic :: Software Development :: Libraries
Classifier: Topic :: Software Development :: Libraries :: Python Modules
Requires-Python: >=3.6
Requires-Dist: pythonnet (>=2.5.1)
Requires-Dist: pandas
Requires-Dist: psutil
Requires-Dist: pywin32
